[
  {
    "title": "ああああ",
    "content": "ああああああああ\n\n\n\n\n\n\n\nああああああああああ",
    "description": "ああああああああ\n\n\n\n\n\n\n\nああああああああああ...",
    "id": 1738754032453,
    "date": "2025-02-05"
  },
  {
    "title": "てえすと",
    "content": "つと\n\nてすと\n\n\nっt\n\nbんkbんkj",
    "description": "つと\n\nてすと\n\n\nっt\n\nbんkbんkj...",
    "id": 1738753979956,
    "date": "2025-02-05"
  },
  {
    "title": "なこなこかっぶる人生上がり",
    "content": "裏やましい",
    "description": "裏やましい...",
    "id": 1738583737965,
    "date": "2025-02-03"
  },
  {
    "title": "60代ファッション。ロングパールネックレス＋ボーダーニットの大人デニムスタイル♪",
    "content": "立春の本日は、空は明るいものの、冷え込みの厳しい一日の予報です。\n\n \n\nそこで、アウターは、足首まで隠れるベンチコートを選び、\n\n \n\nインナーは、ボーダーニットにロールアップデニムを穿き、\n\nあまりにもカジュアルでスポーティーな組み合わせなので💦、\nツイードジャケットを重ね着して、ロングのフェイクパールネックレスを四重にして、ぐるぐる首に巻きました。\n\n \n\nボーダー柄とパールは相性がよく、パールのピアスを付けることもあるのですが、\n\n今日は、黒いコートの面積が広い分、パールの白さを目立たせたくて、ネックレスをパールにしました。\n\nまた、コーデのカジュアルテイストを崩さないために、他のアクセサリーはパールを避け、シルバーのものを付けています。\n\n \n\nバッグはゴールド、ブーツは薄いベージュと、全体の印象が明るくなる色味をプラスしました。\nボーダーニット、バッグ　　GU\n\nデニム　　each\n\nベンチコート　　SISLEY\n\nブーツ　　Dholic\n\nフェイクパールネックレス　　ユナイテッドアローズ\n\n \n\n \n\n \n\n※ファッション以外のテーマで、60代の今感じることや、お料理を始め、日々のあれこれを、別ブログに記録しています。\n\nよろしければ、お時間のある時にお立ち寄り下さいm(_\"_)m",
    "description": "立春の本日は、空は明るいものの、冷え込みの厳しい一日の予報です。\n\n \n\nそこで、アウターは、足首ま...",
    "id": 1738582367039,
    "date": "2025-02-03"
  },
  {
    "title": "大好きな親友のメッセージで、",
    "content": "今日のダンス楽しかったー！\nさくら、やる気がある日は\n頑張れるんだよね〜\nあと、頑張れた日は楽しい！\n\n\n\nえ、わかってるんじゃん！\nそう！\n頑張れると\n楽しいんだよ！\n\n\nそりゃ分かってるよ！でもさ\n仕方なくない？\nやる気出ない日もあるし。\n\n\n\n\n笑\n\n\nごもっともですね。\n\n\n\nまあ、今日が楽しかったんなら\nそれでいいよ！\n\n\n\nあと、大好きな親友の子から\nメールで、\n\n\n『さくちゃん、今日ダンス頑張ってね！応援してるよ♡』って\nメッセージがダンス前にきてたらしくて、\n\n\n終わってから\n親友に電話してて、\n\n○○○ちゃんのおかげで\nさくら、今日楽しく頑張れたよ！ありがとう♡大好きだよ！\n\n\nって話してた🤣🤣🤣\n\n\nあれ、パパパワーかと思ったのに！！\n\nま、どっちでもいいね！笑",
    "description": "今日のダンス楽しかったー！\nさくら、やる気がある日は\n頑張れるんだよね〜\nあと、頑張れた日は楽しい！...",
    "id": 1738494737865,
    "date": "2025-02-02"
  },
  {
    "title": "大好きな親友のメッセージで、",
    "content": "大好きな親友のメッセージで、",
    "description": "大好きな親友のメッセージで、...",
    "id": 1738494678287,
    "date": "2025-02-02"
  },
  {
    "title": "dさふぁ",
    "content": "だsふぁsd",
    "description": "だsふぁsd...",
    "id": 1738494205344,
    "date": "2025-02-02"
  },
  {
    "title": "さdふぁsd",
    "content": "dさふぁsdf",
    "description": "dさふぁsdf...",
    "id": 1738494198628,
    "date": "2025-02-02"
  },
  {
    "title": "sd",
    "content": "sd",
    "description": "sd...",
    "id": 1738493116409,
    "date": "2025-02-02"
  },
  {
    "title": "ああああ",
    "content": "khjkっlkj",
    "description": "khjkっlkj...",
    "id": 1738491700073,
    "date": "2025-02-02"
  },
  {
    "title": "あいうえお",
    "content": "保存",
    "description": "保存...",
    "id": 1738491649090,
    "date": "2025-02-02"
  },
  {
    "title": "さf",
    "content": "あsdf",
    "description": "あsdf...",
    "id": 1738486366125,
    "date": "2025-02-02"
  },
  {
    "title": "fds",
    "content": "dsfg",
    "description": "dsfg...",
    "id": 1738485397619,
    "date": "2025-02-02"
  }
]